LICENSE
README.md
setup.py
pavdedutor/__init__.py
pavdedutor/pavdedutor.py
pavdedutor.egg-info/PKG-INFO
pavdedutor.egg-info/SOURCES.txt
pavdedutor.egg-info/dependency_links.txt
pavdedutor.egg-info/requires.txt
pavdedutor.egg-info/top_level.txt