Metadata-Version: 2.1
Name: pavdedutor
Version: 0.0.3
Summary: Otimizador de uso de ábacos de valores deduzíveis para análise de patologias em pavimentos rígidos e flexíveis
Author: Wellington Moura
Author-email: pro.wmoura@gmail.com
License: MIT
Keywords: dnit pavimento norma ábaco rígido flexível
Classifier: Programming Language :: Python :: 3
Classifier: License :: OSI Approved :: MIT License
Classifier: Operating System :: OS Independent
Requires-Python: >=3.7
License-File: LICENSE
